{
  "id": "boynextdoor-earth-wind-fire",
  "title": "Earth, Wind & Fire",
  "artist": "BOYNEXTDOOR",
  "youtubeId": "u9nP3qXQA4o",
  "words": [
    {
      "korean": "헷갈리다",
      "romanization": "hetgallida",
      "english": "to be confused",
      "spanish": "confundirse",
      "portuguese": "confundir-se",
      "indonesian": "bingung",
      "japanese": "混乱する",
      "thai": "สับสน",
      "french": "être confus",
      "partOfSpeech": "verb",
      "emoji": "😵",
      "example": "길이 너무 헷갈려요.",
      "exampleTranslation": "The route is so confusing.",
      "timestamp": 12.2
    },
    {
      "korean": "참다",
      "romanization": "chamda",
      "english": "to endure",
      "spanish": "aguantar",
      "portuguese": "aguentar",
      "indonesian": "menahan",
      "japanese": "我慢する",
      "thai": "อดทน",
      "french": "supporter",
      "partOfSpeech": "verb",
      "emoji": "😤",
      "example": "화가 났지만 꾹 참았어요.",
      "exampleTranslation": "I was angry but I held it in.",
      "timestamp": 19.2
    },
    {
      "korean": "만들다",
      "romanization": "mandeulda",
      "english": "to make",
      "spanish": "hacer",
      "portuguese": "fazer",
      "indonesian": "membuat",
      "japanese": "作る",
      "thai": "ทำ",
      "french": "faire",
      "partOfSpeech": "verb",
      "emoji": "🛠️",
      "example": "엄마가 케이크를 만들었어요.",
      "exampleTranslation": "Mom made a cake.",
      "timestamp": 31.9
    },
    {
      "korean": "부족하다",
      "romanization": "bujokada",
      "english": "to be insufficient",
      "spanish": "ser insuficiente",
      "portuguese": "ser insuficiente",
      "indonesian": "kurang",
      "japanese": "足りない",
      "thai": "ไม่เพียงพอ",
      "french": "être insuffisant",
      "partOfSpeech": "adjective",
      "emoji": "📉",
      "example": "시간이 조금 부족해요.",
      "exampleTranslation": "Time is a bit insufficient.",
      "timestamp": 52.1
    },
    {
      "korean": "헷갈리다",
      "romanization": "hetgallida",
      "english": "to be confused",
      "spanish": "confundirse",
      "portuguese": "confundir-se",
      "indonesian": "bingung",
      "japanese": "混乱する",
      "thai": "สับสน",
      "french": "être confus",
      "partOfSpeech": "verb",
      "emoji": "😵",
      "example": "두 사람 이름이 자꾸 헷갈려요.",
      "exampleTranslation": "I keep confusing the two names.",
      "timestamp": 62.4
    },
    {
      "korean": "예의",
      "romanization": "yeui",
      "english": "manners",
      "spanish": "modales",
      "portuguese": "boas maneiras",
      "indonesian": "sopan santun",
      "japanese": "礼儀",
      "thai": "มารยาท",
      "french": "politesse",
      "partOfSpeech": "noun",
      "emoji": "🙇",
      "example": "그는 예의가 바른 사람이에요.",
      "exampleTranslation": "He is a well-mannered person.",
      "timestamp": 83.7
    },
    {
      "korean": "하늘",
      "romanization": "haneul",
      "english": "sky",
      "spanish": "cielo",
      "portuguese": "céu",
      "indonesian": "langit",
      "japanese": "空",
      "thai": "ท้องฟ้า",
      "french": "ciel",
      "partOfSpeech": "noun",
      "emoji": "☁️",
      "example": "오늘은 하늘이 참 맑아요.",
      "exampleTranslation": "The sky is so clear today.",
      "timestamp": 95.9
    },
    {
      "korean": "바람",
      "romanization": "baram",
      "english": "wind",
      "spanish": "viento",
      "portuguese": "vento",
      "indonesian": "angin",
      "japanese": "風",
      "thai": "ลม",
      "french": "vent",
      "partOfSpeech": "noun",
      "emoji": "🌬️",
      "example": "시원한 바람이 불어요.",
      "exampleTranslation": "A cool wind is blowing.",
      "timestamp": 102.8
    },
    {
      "korean": "부족하다",
      "romanization": "bujokada",
      "english": "to be insufficient",
      "spanish": "ser insuficiente",
      "portuguese": "ser insuficiente",
      "indonesian": "kurang",
      "japanese": "足りない",
      "thai": "ไม่เพียงพอ",
      "french": "être insuffisant",
      "partOfSpeech": "adjective",
      "emoji": "📉",
      "example": "잠이 늘 부족해요.",
      "exampleTranslation": "I am always short on sleep.",
      "timestamp": 116.4
    },
    {
      "korean": "갈팡질팡",
      "romanization": "galpangjilpang",
      "english": "wavering",
      "spanish": "vacilante",
      "portuguese": "hesitante",
      "indonesian": "bimbang",
      "japanese": "うろうろ",
      "thai": "ลังเล",
      "french": "hésitant",
      "partOfSpeech": "adverb",
      "emoji": "🤷",
      "example": "결정을 못 하고 갈팡질팡했어요.",
      "exampleTranslation": "I wavered, unable to decide.",
      "timestamp": 126.8
    },
    {
      "korean": "잠깐",
      "romanization": "jamkkan",
      "english": "for a moment",
      "spanish": "un momento",
      "portuguese": "um momento",
      "indonesian": "sebentar",
      "japanese": "ちょっと",
      "thai": "สักครู่",
      "french": "un instant",
      "partOfSpeech": "adverb",
      "emoji": "⏸️",
      "example": "잠깐 여기서 기다려 주세요.",
      "exampleTranslation": "Please wait here for a moment.",
      "timestamp": 133.8
    },
    {
      "korean": "숨",
      "romanization": "sum",
      "english": "breath",
      "spanish": "aliento",
      "portuguese": "respiração",
      "indonesian": "napas",
      "japanese": "息",
      "thai": "ลมหายใจ",
      "french": "souffle",
      "partOfSpeech": "noun",
      "emoji": "💨",
      "example": "깊게 숨을 들이쉬었어요.",
      "exampleTranslation": "I took a deep breath.",
      "timestamp": 141.9
    },
    {
      "korean": "헷갈리다",
      "romanization": "hetgallida",
      "english": "to be confused",
      "spanish": "confundirse",
      "portuguese": "confundir-se",
      "indonesian": "bingung",
      "japanese": "混乱する",
      "thai": "สับสน",
      "french": "être confus",
      "partOfSpeech": "verb",
      "emoji": "😵",
      "example": "설명이 복잡해서 헷갈렸어요.",
      "exampleTranslation": "The explanation was complex, so I got confused.",
      "timestamp": 154.9
    }
  ]
}
