{
  "id": "gyeongseoyeji-call-my-name",
  "title": "다정히 내 이름을 부르면",
  "artist": "경서예지",
  "youtubeId": "YPvrhziJAno",
  "words": [
    {
      "korean": "별빛",
      "romanization": "byeolbit",
      "english": "starlight",
      "spanish": "luz de las estrellas",
      "portuguese": "luz das estrelas",
      "indonesian": "cahaya bintang",
      "japanese": "星明かり",
      "thai": "แสงดาว",
      "french": "lumière des étoiles",
      "partOfSpeech": "noun",
      "emoji": "✨",
      "example": "별빛이 밤하늘에 내려요.",
      "exampleTranslation": "Starlight falls on the night sky.",
      "timestamp": 11.6
    },
    {
      "korean": "밤",
      "romanization": "bam",
      "english": "night",
      "spanish": "noche",
      "portuguese": "noite",
      "indonesian": "malam",
      "japanese": "夜",
      "thai": "กลางคืน",
      "french": "nuit",
      "partOfSpeech": "noun",
      "emoji": "🌙",
      "example": "별빛이 내리던 밤이었어요.",
      "exampleTranslation": "It was a night when starlight fell.",
      "timestamp": 11.6
    },
    {
      "korean": "바람",
      "romanization": "baram",
      "english": "wind",
      "spanish": "viento",
      "portuguese": "vento",
      "indonesian": "angin",
      "japanese": "風",
      "thai": "ลม",
      "french": "vent",
      "partOfSpeech": "noun",
      "emoji": "🍃",
      "example": "기분 좋은 바람이 불어요.",
      "exampleTranslation": "A pleasant wind is blowing.",
      "timestamp": 17.7
    },
    {
      "korean": "바다",
      "romanization": "bada",
      "english": "sea",
      "spanish": "mar",
      "portuguese": "mar",
      "indonesian": "laut",
      "japanese": "海",
      "thai": "ทะเล",
      "french": "mer",
      "partOfSpeech": "noun",
      "emoji": "🌊",
      "example": "바다 위를 함께 걸어요.",
      "exampleTranslation": "We walk together over the sea.",
      "timestamp": 17.7
    },
    {
      "korean": "새벽",
      "romanization": "saebyeok",
      "english": "dawn, early morning",
      "spanish": "amanecer",
      "portuguese": "amanhecer",
      "indonesian": "fajar",
      "japanese": "夜明け",
      "thai": "รุ่งอรุณ",
      "french": "aube",
      "partOfSpeech": "noun",
      "emoji": "🌅",
      "example": "새벽 바다를 함께 봤어요.",
      "exampleTranslation": "We watched the dawn sea together.",
      "timestamp": 23.5
    },
    {
      "korean": "손끝",
      "romanization": "sonkkeut",
      "english": "fingertip",
      "spanish": "punta del dedo",
      "portuguese": "ponta do dedo",
      "indonesian": "ujung jari",
      "japanese": "指先",
      "thai": "ปลายนิ้ว",
      "french": "bout du doigt",
      "partOfSpeech": "noun",
      "emoji": "👆",
      "example": "떨린 손끝으로 그림을 그려요.",
      "exampleTranslation": "I draw with trembling fingertips.",
      "timestamp": 34.4
    },
    {
      "korean": "입술",
      "romanization": "ipsul",
      "english": "lips",
      "spanish": "labios",
      "portuguese": "lábios",
      "indonesian": "bibir",
      "japanese": "唇",
      "thai": "ริมฝีปาก",
      "french": "lèvres",
      "partOfSpeech": "noun",
      "emoji": "👄",
      "example": "웃어주는 입술이 예뻐요.",
      "exampleTranslation": "The smiling lips are pretty.",
      "timestamp": 39.3
    },
    {
      "korean": "사랑",
      "romanization": "sarang",
      "english": "love",
      "spanish": "amor",
      "portuguese": "amor",
      "indonesian": "cinta",
      "japanese": "愛",
      "thai": "ความรัก",
      "french": "amour",
      "partOfSpeech": "noun",
      "emoji": "❤️",
      "example": "내 사랑도 피어나요.",
      "exampleTranslation": "My love also blooms.",
      "timestamp": 47.6
    },
    {
      "korean": "이름",
      "romanization": "ireum",
      "english": "name",
      "spanish": "nombre",
      "portuguese": "nome",
      "indonesian": "nama",
      "japanese": "名前",
      "thai": "ชื่อ",
      "french": "nom",
      "partOfSpeech": "noun",
      "emoji": "📛",
      "example": "다정히 내 이름을 불러 줘요.",
      "exampleTranslation": "Lovingly call my name.",
      "timestamp": 51.5
    },
    {
      "korean": "마음",
      "romanization": "maeum",
      "english": "heart, mind",
      "spanish": "corazón",
      "portuguese": "coração",
      "indonesian": "hati",
      "japanese": "心",
      "thai": "ใจ",
      "french": "cœur",
      "partOfSpeech": "noun",
      "emoji": "💗",
      "example": "내 마음이 녹아내려요.",
      "exampleTranslation": "My heart melts away.",
      "timestamp": 51.5
    },
    {
      "korean": "선물",
      "romanization": "seonmul",
      "english": "gift, present",
      "spanish": "regalo",
      "portuguese": "presente",
      "indonesian": "hadiah",
      "japanese": "贈り物",
      "thai": "ของขวัญ",
      "french": "cadeau",
      "partOfSpeech": "noun",
      "emoji": "🎁",
      "example": "너는 나에게 선물 같아.",
      "exampleTranslation": "You are like a gift to me.",
      "timestamp": 64.5
    },
    {
      "korean": "하늘",
      "romanization": "haneul",
      "english": "sky",
      "spanish": "cielo",
      "portuguese": "céu",
      "indonesian": "langit",
      "japanese": "空",
      "thai": "ท้องฟ้า",
      "french": "ciel",
      "partOfSpeech": "noun",
      "emoji": "☁️",
      "example": "하늘 아래 너와 나뿐이에요.",
      "exampleTranslation": "Under the sky, it's just you and me.",
      "timestamp": 74.7
    },
    {
      "korean": "봄꽃",
      "romanization": "bomkkot",
      "english": "spring flower",
      "spanish": "flor de primavera",
      "portuguese": "flor da primavera",
      "indonesian": "bunga musim semi",
      "japanese": "春の花",
      "thai": "ดอกไม้ฤดูใบไม้ผลิ",
      "french": "fleur de printemps",
      "partOfSpeech": "noun",
      "emoji": "🌸",
      "example": "5월에 피는 봄꽃처럼 예뻐요.",
      "exampleTranslation": "Pretty like a spring flower blooming in May.",
      "timestamp": 106.1
    },
    {
      "korean": "꿈",
      "romanization": "kkum",
      "english": "dream",
      "spanish": "sueño",
      "portuguese": "sonho",
      "indonesian": "mimpi",
      "japanese": "夢",
      "thai": "ความฝัน",
      "french": "rêve",
      "partOfSpeech": "noun",
      "emoji": "💭",
      "example": "이건 꿈이 아니에요.",
      "exampleTranslation": "This is not a dream.",
      "timestamp": 148.0
    },
    {
      "korean": "인생",
      "romanization": "insaeng",
      "english": "life",
      "spanish": "vida",
      "portuguese": "vida",
      "indonesian": "kehidupan",
      "japanese": "人生",
      "thai": "ชีวิต",
      "french": "vie",
      "partOfSpeech": "noun",
      "emoji": "🌱",
      "example": "너는 내 인생의 전부예요.",
      "exampleTranslation": "You are my whole life.",
      "timestamp": 174.4
    },
    {
      "korean": "그림자",
      "romanization": "geurimja",
      "english": "shadow",
      "spanish": "sombra",
      "portuguese": "sombra",
      "indonesian": "bayangan",
      "japanese": "影",
      "thai": "เงา",
      "french": "ombre",
      "partOfSpeech": "noun",
      "emoji": "🌑",
      "example": "별빛 아래 우리 그림자가 겹쳐요.",
      "exampleTranslation": "Under the starlight, our shadows overlap.",
      "timestamp": 187.7
    },
    {
      "korean": "겨울",
      "romanization": "gyeoul",
      "english": "winter",
      "spanish": "invierno",
      "portuguese": "inverno",
      "indonesian": "musim dingin",
      "japanese": "冬",
      "thai": "ฤดูหนาว",
      "french": "hiver",
      "partOfSpeech": "noun",
      "emoji": "❄️",
      "example": "길고 긴 겨울이 끝났어요.",
      "exampleTranslation": "The long, long winter has ended.",
      "timestamp": 194.5
    },
    {
      "korean": "목소리",
      "romanization": "moksori",
      "english": "voice",
      "spanish": "voz",
      "portuguese": "voz",
      "indonesian": "suara",
      "japanese": "声",
      "thai": "เสียง",
      "french": "voix",
      "partOfSpeech": "noun",
      "emoji": "🗣️",
      "example": "선명한 목소리로 말했어요.",
      "exampleTranslation": "I spoke in a clear voice.",
      "timestamp": 201.4
    }
  ]
}