{
  "id": "ive-i-am",
  "title": "I AM",
  "artist": "IVE",
  "youtubeId": "6ZUIwj3FgUY",
  "words": [
    {
      "korean": "다른",
      "romanization": "dareun",
      "english": "different, other",
      "spanish": "diferente",
      "portuguese": "diferente",
      "indonesian": "berbeda",
      "japanese": "違う",
      "thai": "ที่แตกต่าง",
      "french": "différent",
      "partOfSpeech": "adjective",
      "emoji": "🔀",
      "example": "나는 다른 노래를 듣고 싶어.",
      "exampleTranslation": "I want to listen to a different song.",
      "timestamp": 6.0
    },
    {
      "korean": "문을",
      "romanization": "muneul",
      "english": "door (object)",
      "spanish": "la puerta",
      "portuguese": "a porta",
      "indonesian": "pintu",
      "japanese": "ドアを",
      "thai": "ประตู",
      "french": "la porte",
      "partOfSpeech": "noun",
      "emoji": "🚪",
      "example": "문을 조용히 열었어.",
      "exampleTranslation": "I opened the door quietly.",
      "timestamp": 6.0
    },
    {
      "korean": "열어",
      "romanization": "yeoreo",
      "english": "open",
      "spanish": "abrir",
      "portuguese": "abrir",
      "indonesian": "buka",
      "japanese": "開ける",
      "thai": "เปิด",
      "french": "ouvrir",
      "partOfSpeech": "verb",
      "emoji": "🔓",
      "example": "창문을 열어 줄래?",
      "exampleTranslation": "Can you open the window?",
      "timestamp": 6.0
    },
    {
      "korean": "필요는",
      "romanization": "piryoneun",
      "english": "need (topic)",
      "spanish": "la necesidad",
      "portuguese": "a necessidade",
      "indonesian": "kebutuhan",
      "japanese": "必要は",
      "thai": "ความจำเป็น",
      "french": "le besoin",
      "partOfSpeech": "noun",
      "emoji": "❗",
      "example": "지금은 휴식이 필요는 해.",
      "exampleTranslation": "Right now, I do need some rest.",
      "timestamp": 6.0
    },
    {
      "korean": "길로",
      "romanization": "gillo",
      "english": "by the road, by the way",
      "spanish": "por el camino",
      "portuguese": "pelo caminho",
      "indonesian": "melalui jalan",
      "japanese": "道へ",
      "thai": "ไปตามทาง",
      "french": "par le chemin",
      "partOfSpeech": "noun",
      "emoji": "🛤️",
      "example": "새로운 길로 가 보자.",
      "exampleTranslation": "Let's go by a new way.",
      "timestamp": 10.1
    },
    {
      "korean": "하루하루마다",
      "romanization": "haruharumada",
      "english": "every single day",
      "spanish": "cada día",
      "portuguese": "a cada dia",
      "indonesian": "setiap hari",
      "japanese": "一日一日",
      "thai": "ทุกๆวัน",
      "french": "chaque jour",
      "partOfSpeech": "adverb",
      "emoji": "📅",
      "example": "하루하루마다 조금씩 성장해.",
      "exampleTranslation": "I grow a little every single day.",
      "timestamp": 13.8
    },
    {
      "korean": "느낌",
      "romanization": "neukkim",
      "english": "feeling",
      "spanish": "sensación",
      "portuguese": "sensação",
      "indonesian": "perasaan",
      "japanese": "感じ",
      "thai": "ความรู้สึก",
      "french": "sensation",
      "partOfSpeech": "noun",
      "emoji": "💫",
      "example": "오늘은 기분 좋은 느낌이야.",
      "exampleTranslation": "Today has a nice feeling.",
      "timestamp": 13.8
    },
    {
      "korean": "밝게",
      "romanization": "balgge",
      "english": "brightly",
      "spanish": "brillantemente",
      "portuguese": "brilhantemente",
      "indonesian": "dengan cerah",
      "japanese": "明るく",
      "thai": "อย่างสว่างไสว",
      "french": "brillamment",
      "partOfSpeech": "adverb",
      "emoji": "☀️",
      "example": "오늘도 밝게 웃어 줘.",
      "exampleTranslation": "Smile brightly today too.",
      "timestamp": 17.8
    },
    {
      "korean": "빛이",
      "romanization": "bichi",
      "english": "light (subject)",
      "spanish": "la luz",
      "portuguese": "a luz",
      "indonesian": "cahaya",
      "japanese": "光が",
      "thai": "แสง",
      "french": "la lumière",
      "partOfSpeech": "noun",
      "emoji": "✨",
      "example": "창문 사이로 빛이 들어와.",
      "exampleTranslation": "Light comes in through the window.",
      "timestamp": 17.8
    },
    {
      "korean": "찾아",
      "romanization": "chaja",
      "english": "find, search for",
      "spanish": "buscar",
      "portuguese": "procurar",
      "indonesian": "mencari",
      "japanese": "探す",
      "thai": "ค้นหา",
      "french": "chercher",
      "partOfSpeech": "verb",
      "emoji": "🔍",
      "example": "잃어버린 지갑을 찾아 다녔어.",
      "exampleTranslation": "I went around looking for my lost wallet.",
      "timestamp": 17.8
    },
    {
      "korean": "그냥",
      "romanization": "geunyang",
      "english": "just, simply",
      "spanish": "simplemente",
      "portuguese": "simplesmente",
      "indonesian": "hanya saja",
      "japanese": "ただ",
      "thai": "แค่",
      "french": "simplement",
      "partOfSpeech": "adverb",
      "emoji": "🤷",
      "example": "그냥 네 생각이 났어.",
      "exampleTranslation": "I just thought of you.",
      "timestamp": 20.2
    },
    {
      "korean": "믿으면",
      "romanization": "mideumyeon",
      "english": "if (I) believe",
      "spanish": "si creo",
      "portuguese": "se acredito",
      "indonesian": "jika percaya",
      "japanese": "信じれば",
      "thai": "ถ้าเชื่อ",
      "french": "si je crois",
      "partOfSpeech": "verb",
      "emoji": "🤞",
      "example": "널 믿으면 다 잘될 거야.",
      "exampleTranslation": "If I believe in you, everything will be fine.",
      "timestamp": 20.2
    },
    {
      "korean": "제일",
      "romanization": "jeil",
      "english": "the most",
      "spanish": "lo más",
      "portuguese": "o mais",
      "indonesian": "paling",
      "japanese": "一番",
      "thai": "มากที่สุด",
      "french": "le plus",
      "partOfSpeech": "adverb",
      "emoji": "🥇",
      "example": "이 노래가 제일 좋아.",
      "exampleTranslation": "I like this song the most.",
      "timestamp": 39.7
    },
    {
      "korean": "어느",
      "romanization": "eoneu",
      "english": "which, some",
      "spanish": "cuál",
      "portuguese": "qual",
      "indonesian": "yang mana",
      "japanese": "どの",
      "thai": "ซึ่ง",
      "french": "quel",
      "partOfSpeech": "adjective",
      "emoji": "❓",
      "example": "어느 길로 가야 할까?",
      "exampleTranslation": "Which way should I go?",
      "timestamp": 39.7
    },
    {
      "korean": "낯선",
      "romanization": "natseon",
      "english": "unfamiliar, strange",
      "spanish": "desconocido",
      "portuguese": "desconhecido",
      "indonesian": "asing",
      "japanese": "見知らぬ",
      "thai": "ที่ไม่คุ้นเคย",
      "french": "inconnu",
      "partOfSpeech": "adjective",
      "emoji": "🌫️",
      "example": "낯선 도시에 도착했어.",
      "exampleTranslation": "I arrived in an unfamiliar city.",
      "timestamp": 44.0
    },
    {
      "korean": "아름다운",
      "romanization": "areumdaun",
      "english": "beautiful",
      "spanish": "hermoso",
      "portuguese": "bonito",
      "indonesian": "indah",
      "japanese": "美しい",
      "thai": "สวยงาม",
      "french": "beau",
      "partOfSpeech": "adjective",
      "emoji": "🌸",
      "example": "오늘 밤하늘이 정말 아름다운 것 같아.",
      "exampleTranslation": "Tonight's sky seems really beautiful.",
      "timestamp": 52.1
    },
    {
      "korean": "판타지",
      "romanization": "pantaji",
      "english": "fantasy",
      "spanish": "fantasía",
      "portuguese": "fantasia",
      "indonesian": "fantasi",
      "japanese": "ファンタジー",
      "thai": "แฟนตาซี",
      "french": "fantaisie",
      "partOfSpeech": "noun",
      "emoji": "🦄",
      "example": "이 영화는 완전 판타지야.",
      "exampleTranslation": "This movie is a total fantasy.",
      "timestamp": 56.1
    },
    {
      "korean": "두려운",
      "romanization": "duryeoun",
      "english": "fearful, scary",
      "spanish": "temeroso",
      "portuguese": "temeroso",
      "indonesian": "menakutkan",
      "japanese": "恐ろしい",
      "thai": "ที่น่ากลัว",
      "french": "effrayant",
      "partOfSpeech": "adjective",
      "emoji": "😱",
      "example": "새로운 시작은 늘 두려운 법이야.",
      "exampleTranslation": "A new beginning is always a bit scary.",
      "timestamp": 72.2
    },
    {
      "korean": "설레게",
      "romanization": "seollege",
      "english": "to make (one's heart) flutter",
      "spanish": "emocionar",
      "portuguese": "emocionar",
      "indonesian": "membuat berdebar",
      "japanese": "ときめかせる",
      "thai": "ทำให้ตื่นเต้น",
      "french": "faire palpiter",
      "partOfSpeech": "verb",
      "emoji": "💓",
      "example": "그 소식이 나를 설레게 했어.",
      "exampleTranslation": "That news made my heart flutter.",
      "timestamp": 72.2
    },
    {
      "korean": "깊은",
      "romanization": "gipeun",
      "english": "deep",
      "spanish": "profundo",
      "portuguese": "profundo",
      "indonesian": "dalam",
      "japanese": "深い",
      "thai": "ลึก",
      "french": "profond",
      "partOfSpeech": "adjective",
      "emoji": "🌊",
      "example": "깊은 밤에 혼자 걸었어.",
      "exampleTranslation": "I walked alone deep in the night.",
      "timestamp": 130.6
    }
  ]
}