{
  "id": "jannabi-for-lovers-who-hesitate",
  "title": "주저하는 연인들을 위해 (For Lovers Who Hesitate)",
  "artist": "잔나비 (JANNABI)",
  "youtubeId": "GpQ222I1ULc",
  "words": [
    {
      "korean": "마음",
      "romanization": "maeum",
      "english": "heart, mind",
      "spanish": "corazón",
      "portuguese": "coração",
      "indonesian": "hati",
      "japanese": "心",
      "thai": "จิตใจ",
      "french": "cœur",
      "partOfSpeech": "noun",
      "emoji": "💗",
      "example": "내 마음을 알아줘.",
      "exampleTranslation": "Please understand my heart.",
      "timestamp": 7.5
    },
    {
      "korean": "당신",
      "romanization": "dangsin",
      "english": "you (polite)",
      "spanish": "usted",
      "portuguese": "você",
      "indonesian": "Anda",
      "japanese": "あなた",
      "thai": "คุณ",
      "french": "vous",
      "partOfSpeech": "noun",
      "emoji": "💑",
      "example": "당신을 믿어요.",
      "exampleTranslation": "I trust you.",
      "timestamp": 13.3
    },
    {
      "korean": "외로운",
      "romanization": "oeroun",
      "english": "lonely",
      "spanish": "solitario",
      "portuguese": "solitário",
      "indonesian": "kesepian",
      "japanese": "寂しい",
      "thai": "เหงา",
      "french": "solitaire",
      "partOfSpeech": "adjective",
      "emoji": "🌙",
      "example": "외로운 밤이에요.",
      "exampleTranslation": "It is a lonely night.",
      "timestamp": 20.8
    },
    {
      "korean": "여운",
      "romanization": "yeoun",
      "english": "lingering feeling, afterglow",
      "spanish": "resonancia",
      "portuguese": "ressonância",
      "indonesian": "kesan mendalam",
      "japanese": "余韻",
      "thai": "ความรู้สึกค้างคา",
      "french": "résonance",
      "partOfSpeech": "noun",
      "emoji": "🌫️",
      "example": "영화의 여운이 길었어요.",
      "exampleTranslation": "The movie left a long afterglow.",
      "timestamp": 33.5
    },
    {
      "korean": "사랑",
      "romanization": "sarang",
      "english": "love",
      "spanish": "amor",
      "portuguese": "amor",
      "indonesian": "cinta",
      "japanese": "愛",
      "thai": "ความรัก",
      "french": "amour",
      "partOfSpeech": "noun",
      "emoji": "❤️",
      "example": "사랑은 아름다워요.",
      "exampleTranslation": "Love is beautiful.",
      "timestamp": 39.3
    },
    {
      "korean": "새하얀",
      "romanization": "saehayan",
      "english": "pure white",
      "spanish": "blanco puro",
      "portuguese": "branco puro",
      "indonesian": "putih bersih",
      "japanese": "真っ白な",
      "thai": "ขาวบริสุทธิ์",
      "french": "blanc pur",
      "partOfSpeech": "adjective",
      "emoji": "🤍",
      "example": "새하얀 눈이 내렸어요.",
      "exampleTranslation": "Pure white snow fell.",
      "timestamp": 52.5
    },
    {
      "korean": "빛",
      "romanization": "bit",
      "english": "light",
      "spanish": "luz",
      "portuguese": "luz",
      "indonesian": "cahaya",
      "japanese": "光",
      "thai": "แสง",
      "french": "lumière",
      "partOfSpeech": "noun",
      "emoji": "✨",
      "example": "빛이 창문으로 들어와요.",
      "exampleTranslation": "Light comes in through the window.",
      "timestamp": 52.5
    },
    {
      "korean": "밤",
      "romanization": "bam",
      "english": "night",
      "spanish": "noche",
      "portuguese": "noite",
      "indonesian": "malam",
      "japanese": "夜",
      "thai": "กลางคืน",
      "french": "nuit",
      "partOfSpeech": "noun",
      "emoji": "🌃",
      "example": "밤에 별을 봤어요.",
      "exampleTranslation": "I saw stars at night.",
      "timestamp": 58.0
    },
    {
      "korean": "비밀",
      "romanization": "bimil",
      "english": "secret",
      "spanish": "secreto",
      "portuguese": "segredo",
      "indonesian": "rahasia",
      "japanese": "秘密",
      "thai": "ความลับ",
      "french": "secret",
      "partOfSpeech": "noun",
      "emoji": "🤫",
      "example": "이건 우리만의 비밀이야.",
      "exampleTranslation": "This is our own secret.",
      "timestamp": 65.4
    },
    {
      "korean": "추억",
      "romanization": "chueok",
      "english": "memory, reminiscence",
      "spanish": "recuerdo",
      "portuguese": "lembrança",
      "indonesian": "kenangan",
      "japanese": "思い出",
      "thai": "ความทรงจำ",
      "french": "souvenir",
      "partOfSpeech": "noun",
      "emoji": "📸",
      "example": "좋은 추억을 만들었어요.",
      "exampleTranslation": "We made good memories.",
      "timestamp": 72.1
    },
    {
      "korean": "남몰래",
      "romanization": "nammollae",
      "english": "secretly, without others knowing",
      "spanish": "a escondidas",
      "portuguese": "às escondidas",
      "indonesian": "diam-diam",
      "japanese": "人知れず",
      "thai": "อย่างลับ ๆ",
      "french": "en cachette",
      "partOfSpeech": "adverb",
      "emoji": "🤭",
      "example": "남몰래 선물을 준비했어요.",
      "exampleTranslation": "I secretly prepared a gift.",
      "timestamp": 78.8
    },
    {
      "korean": "미련",
      "romanization": "miryeon",
      "english": "lingering attachment, regret",
      "spanish": "apego",
      "portuguese": "apego",
      "indonesian": "rasa tak rela",
      "japanese": "未練",
      "thai": "ความอาลัย",
      "french": "attachement",
      "partOfSpeech": "noun",
      "emoji": "💔",
      "example": "미련 없이 떠났어요.",
      "exampleTranslation": "I left without any regrets.",
      "timestamp": 111.3
    },
    {
      "korean": "그리워",
      "romanization": "geuriwo",
      "english": "I miss (someone/something)",
      "spanish": "extraño",
      "portuguese": "sinto saudade",
      "indonesian": "rindu",
      "japanese": "恋しい",
      "thai": "คิดถึง",
      "french": "ça me manque",
      "partOfSpeech": "verb",
      "emoji": "🥺",
      "example": "고향이 그리워요.",
      "exampleTranslation": "I miss my hometown.",
      "timestamp": 111.3
    },
    {
      "korean": "안녕",
      "romanization": "annyeong",
      "english": "hello, goodbye",
      "spanish": "hola, adiós",
      "portuguese": "olá, tchau",
      "indonesian": "halo, selamat tinggal",
      "japanese": "こんにちは、さようなら",
      "thai": "สวัสดี, ลาก่อน",
      "french": "salut, au revoir",
      "partOfSpeech": "expression",
      "emoji": "👋",
      "example": "친구에게 안녕이라고 말했어요.",
      "exampleTranslation": "I said goodbye to my friend.",
      "timestamp": 171.4
    },
    {
      "korean": "계절",
      "romanization": "gyejeol",
      "english": "season",
      "spanish": "estación",
      "portuguese": "estação",
      "indonesian": "musim",
      "japanese": "季節",
      "thai": "ฤดู",
      "french": "saison",
      "partOfSpeech": "noun",
      "emoji": "🍂",
      "example": "제일 좋아하는 계절은 봄이에요.",
      "exampleTranslation": "My favorite season is spring.",
      "timestamp": 207.0
    },
    {
      "korean": "활짝",
      "romanization": "hwaljjak",
      "english": "wide open, in full bloom",
      "spanish": "en plena flor",
      "portuguese": "em plena flor",
      "indonesian": "mekar penuh",
      "japanese": "ぱっと",
      "thai": "บานสะพรั่ง",
      "french": "en pleine floraison",
      "partOfSpeech": "adverb",
      "emoji": "🌸",
      "example": "꽃이 활짝 피었어요.",
      "exampleTranslation": "The flowers bloomed fully.",
      "timestamp": 213.6
    },
    {
      "korean": "영원히",
      "romanization": "yeongwonhi",
      "english": "forever",
      "spanish": "para siempre",
      "portuguese": "para sempre",
      "indonesian": "selamanya",
      "japanese": "永遠に",
      "thai": "ตลอดไป",
      "french": "pour toujours",
      "partOfSpeech": "adverb",
      "emoji": "♾️",
      "example": "영원히 기억할게요.",
      "exampleTranslation": "I will remember it forever.",
      "timestamp": 220.9
    },
    {
      "korean": "꿈",
      "romanization": "kkum",
      "english": "dream",
      "spanish": "sueño",
      "portuguese": "sonho",
      "indonesian": "mimpi",
      "japanese": "夢",
      "thai": "ความฝัน",
      "french": "rêve",
      "partOfSpeech": "noun",
      "emoji": "💭",
      "example": "어젯밤 좋은 꿈을 꿨어요.",
      "exampleTranslation": "I had a good dream last night.",
      "timestamp": 230.9
    }
  ]
}