{
  "id": "melomance-gift",
  "title": "선물 (Gift)",
  "artist": "멜로망스 (MeloMance)",
  "youtubeId": "1ypg_P-pLHQ",
  "words": [
    {
      "korean": "빛",
      "romanization": "bit",
      "english": "light",
      "spanish": "luz",
      "portuguese": "luz",
      "indonesian": "cahaya",
      "japanese": "光",
      "thai": "แสง",
      "french": "lumière",
      "partOfSpeech": "noun",
      "emoji": "💡",
      "example": "방에 빛이 들어와요.",
      "exampleTranslation": "Light comes into the room.",
      "timestamp": 14.5
    },
    {
      "korean": "눈빛",
      "romanization": "nunbit",
      "english": "gaze, look in one's eyes",
      "spanish": "mirada",
      "portuguese": "olhar",
      "indonesian": "tatapan",
      "japanese": "眼差し",
      "thai": "แววตา",
      "french": "regard",
      "partOfSpeech": "noun",
      "emoji": "👁️",
      "example": "따뜻한 눈빛으로 봤어요.",
      "exampleTranslation": "He looked at me with warm eyes.",
      "timestamp": 22.9
    },
    {
      "korean": "사랑",
      "romanization": "sarang",
      "english": "love",
      "spanish": "amor",
      "portuguese": "amor",
      "indonesian": "cinta",
      "japanese": "愛",
      "thai": "ความรัก",
      "french": "amour",
      "partOfSpeech": "noun",
      "emoji": "💕",
      "example": "사랑에 빠졌어요.",
      "exampleTranslation": "I fell in love.",
      "timestamp": 30.4
    },
    {
      "korean": "항상",
      "romanization": "hangsang",
      "english": "always",
      "spanish": "siempre",
      "portuguese": "sempre",
      "indonesian": "selalu",
      "japanese": "いつも",
      "thai": "เสมอ",
      "french": "toujours",
      "partOfSpeech": "adverb",
      "emoji": "🔁",
      "example": "그는 항상 일찍 와요.",
      "exampleTranslation": "He always comes early.",
      "timestamp": 35.2
    },
    {
      "korean": "새롭게",
      "romanization": "saeropge",
      "english": "newly, freshly",
      "spanish": "de nuevo",
      "portuguese": "de forma nova",
      "indonesian": "secara baru",
      "japanese": "新しく",
      "thai": "อย่างใหม่",
      "french": "de façon nouvelle",
      "partOfSpeech": "adverb",
      "emoji": "🆕",
      "example": "새롭게 시작해요.",
      "exampleTranslation": "Let's start fresh.",
      "timestamp": 44.0
    },
    {
      "korean": "설레는",
      "romanization": "seolleneun",
      "english": "heart-fluttering",
      "spanish": "emocionante",
      "portuguese": "emocionante",
      "indonesian": "berdebar",
      "japanese": "ときめく",
      "thai": "ใจเต้น",
      "french": "palpitant",
      "partOfSpeech": "adjective",
      "emoji": "🦋",
      "example": "설레는 마음으로 기다렸어요.",
      "exampleTranslation": "I waited with a fluttering heart.",
      "timestamp": 50.0
    },
    {
      "korean": "선물",
      "romanization": "seonmul",
      "english": "gift, present",
      "spanish": "regalo",
      "portuguese": "presente",
      "indonesian": "hadiah",
      "japanese": "プレゼント",
      "thai": "ของขวัญ",
      "french": "cadeau",
      "partOfSpeech": "noun",
      "emoji": "🎁",
      "example": "생일 선물을 받았어요.",
      "exampleTranslation": "I received a birthday gift.",
      "timestamp": 61.6
    },
    {
      "korean": "모든",
      "romanization": "modeun",
      "english": "every, all",
      "spanish": "todo",
      "portuguese": "todo",
      "indonesian": "semua",
      "japanese": "すべての",
      "thai": "ทั้งหมด",
      "french": "tout",
      "partOfSpeech": "adjective",
      "emoji": "🌐",
      "example": "모든 게 새로워 보여요.",
      "exampleTranslation": "Everything looks new.",
      "timestamp": 67.9
    },
    {
      "korean": "평범했던",
      "romanization": "pyeongbeomhaetdeon",
      "english": "that used to be ordinary",
      "spanish": "que era ordinario",
      "portuguese": "que era comum",
      "indonesian": "yang dulu biasa",
      "japanese": "平凡だった",
      "thai": "ที่เคยธรรมดา",
      "french": "qui était ordinaire",
      "partOfSpeech": "adjective",
      "emoji": "😐",
      "example": "평범했던 하루가 특별해졌어요.",
      "exampleTranslation": "An ordinary day became special.",
      "timestamp": 74.3
    },
    {
      "korean": "일상",
      "romanization": "ilsang",
      "english": "daily life",
      "spanish": "vida cotidiana",
      "portuguese": "cotidiano",
      "indonesian": "keseharian",
      "japanese": "日常",
      "thai": "ชีวิตประจำวัน",
      "french": "quotidien",
      "partOfSpeech": "noun",
      "emoji": "🏠",
      "example": "일상이 즐거워요.",
      "exampleTranslation": "My daily life is enjoyable.",
      "timestamp": 74.3
    },
    {
      "korean": "특별해지는",
      "romanization": "teukbyeolhaejineun",
      "english": "becoming special",
      "spanish": "que se vuelve especial",
      "portuguese": "que se torna especial",
      "indonesian": "menjadi istimewa",
      "japanese": "特別になる",
      "thai": "ที่กลายเป็นพิเศษ",
      "french": "qui devient spécial",
      "partOfSpeech": "adjective",
      "emoji": "🌟",
      "example": "너와 있으면 특별해지는 기분이야.",
      "exampleTranslation": "I feel special when I'm with you.",
      "timestamp": 80.3
    },
    {
      "korean": "순간",
      "romanization": "sungan",
      "english": "moment",
      "spanish": "momento",
      "portuguese": "momento",
      "indonesian": "momen",
      "japanese": "瞬間",
      "thai": "ช่วงเวลา",
      "french": "moment",
      "partOfSpeech": "noun",
      "emoji": "✨",
      "example": "행복한 순간이었어요.",
      "exampleTranslation": "It was a happy moment.",
      "timestamp": 80.3
    },
    {
      "korean": "예뻐",
      "romanization": "yeppeo",
      "english": "pretty",
      "spanish": "bonita",
      "portuguese": "bonita",
      "indonesian": "cantik",
      "japanese": "きれいだ",
      "thai": "สวย",
      "french": "jolie",
      "partOfSpeech": "adjective",
      "emoji": "😍",
      "example": "오늘 정말 예뻐 보여요.",
      "exampleTranslation": "You look really pretty today.",
      "timestamp": 104.0
    },
    {
      "korean": "어두웠던",
      "romanization": "eoduwotdeon",
      "english": "that used to be dark",
      "spanish": "que era oscuro",
      "portuguese": "que era escuro",
      "indonesian": "yang dulu gelap",
      "japanese": "暗かった",
      "thai": "ที่เคยมืด",
      "french": "qui était sombre",
      "partOfSpeech": "adjective",
      "emoji": "🌑",
      "example": "어두웠던 방이 밝아졌어요.",
      "exampleTranslation": "The dark room became bright.",
      "timestamp": 116.3
    },
    {
      "korean": "아이",
      "romanization": "ai",
      "english": "child",
      "spanish": "niño",
      "portuguese": "criança",
      "indonesian": "anak",
      "japanese": "子供",
      "thai": "เด็ก",
      "french": "enfant",
      "partOfSpeech": "noun",
      "emoji": "👶",
      "example": "아이처럼 신나게 놀았어요.",
      "exampleTranslation": "I played excitedly like a child.",
      "timestamp": 183.8
    },
    {
      "korean": "순수한",
      "romanization": "sunsuhan",
      "english": "pure, innocent",
      "spanish": "puro",
      "portuguese": "puro",
      "indonesian": "murni",
      "japanese": "純粋な",
      "thai": "บริสุทธิ์",
      "french": "pur",
      "partOfSpeech": "adjective",
      "emoji": "🤍",
      "example": "순수한 마음으로 도와줬어요.",
      "exampleTranslation": "I helped with a pure heart.",
      "timestamp": 188.3
    }
  ]
}