{
  "id": "parkdahye-child-of-beginning",
  "title": "시작의 아이 (Starting With You)",
  "artist": "박다혜 (Park Dahye), 마크툽 (MAKTUB)",
  "youtubeId": "aA9D4tJcAm4",
  "words": [
    {
      "korean": "존재",
      "romanization": "jonjae",
      "english": "existence, being",
      "spanish": "existencia",
      "portuguese": "existência",
      "indonesian": "keberadaan",
      "japanese": "存在",
      "thai": "การมีอยู่",
      "french": "existence",
      "partOfSpeech": "noun",
      "emoji": "✨",
      "example": "그의 존재가 큰 힘이 돼요.",
      "exampleTranslation": "His existence is a great strength.",
      "timestamp": 13.1
    },
    {
      "korean": "달",
      "romanization": "dal",
      "english": "moon",
      "spanish": "luna",
      "portuguese": "lua",
      "indonesian": "bulan",
      "japanese": "月",
      "thai": "ดวงจันทร์",
      "french": "lune",
      "partOfSpeech": "noun",
      "emoji": "🌙",
      "example": "밤하늘에 달이 밝아요.",
      "exampleTranslation": "The moon is bright in the night sky.",
      "timestamp": 26.0
    },
    {
      "korean": "세상",
      "romanization": "sesang",
      "english": "world",
      "spanish": "mundo",
      "portuguese": "mundo",
      "indonesian": "dunia",
      "japanese": "世界",
      "thai": "โลก",
      "french": "monde",
      "partOfSpeech": "noun",
      "emoji": "🌍",
      "example": "세상은 넓고 아름다워요.",
      "exampleTranslation": "The world is vast and beautiful.",
      "timestamp": 38.8
    },
    {
      "korean": "시간",
      "romanization": "sigan",
      "english": "time",
      "spanish": "tiempo",
      "portuguese": "tempo",
      "indonesian": "waktu",
      "japanese": "時間",
      "thai": "เวลา",
      "french": "temps",
      "partOfSpeech": "noun",
      "emoji": "⏰",
      "example": "시간이 정말 빨리 가요.",
      "exampleTranslation": "Time really flies.",
      "timestamp": 51.6
    },
    {
      "korean": "이름",
      "romanization": "ireum",
      "english": "name",
      "spanish": "nombre",
      "portuguese": "nome",
      "indonesian": "nama",
      "japanese": "名前",
      "thai": "ชื่อ",
      "french": "nom",
      "partOfSpeech": "noun",
      "emoji": "📛",
      "example": "새 강아지의 이름을 지었어요.",
      "exampleTranslation": "I named my new puppy.",
      "timestamp": 65.3
    },
    {
      "korean": "기적",
      "romanization": "gijeok",
      "english": "miracle",
      "spanish": "milagro",
      "portuguese": "milagre",
      "indonesian": "keajaiban",
      "japanese": "奇跡",
      "thai": "ปาฏิหาริย์",
      "french": "miracle",
      "partOfSpeech": "noun",
      "emoji": "🌟",
      "example": "그것은 정말 기적 같은 일이에요.",
      "exampleTranslation": "That is truly like a miracle.",
      "timestamp": 78.1
    },
    {
      "korean": "멈추다",
      "romanization": "meomchuda",
      "english": "to stop",
      "spanish": "detenerse",
      "portuguese": "parar",
      "indonesian": "berhenti",
      "japanese": "止まる",
      "thai": "หยุด",
      "french": "s'arrêter",
      "partOfSpeech": "verb",
      "emoji": "✋",
      "example": "갑자기 비가 멈췄어요.",
      "exampleTranslation": "The rain suddenly stopped.",
      "timestamp": 84.7
    },
    {
      "korean": "예쁘다",
      "romanization": "yeppeuda",
      "english": "to be pretty",
      "spanish": "ser bonito",
      "portuguese": "ser bonito",
      "indonesian": "cantik",
      "japanese": "きれいだ",
      "thai": "สวย",
      "french": "être joli",
      "partOfSpeech": "adjective",
      "emoji": "🌸",
      "example": "이 꽃이 정말 예뻐요.",
      "exampleTranslation": "This flower is really pretty.",
      "timestamp": 98.1
    },
    {
      "korean": "찾다",
      "romanization": "chatda",
      "english": "to find, to look for",
      "spanish": "buscar",
      "portuguese": "procurar",
      "indonesian": "mencari",
      "japanese": "探す",
      "thai": "หา",
      "french": "chercher",
      "partOfSpeech": "verb",
      "emoji": "🔍",
      "example": "잃어버린 열쇠를 찾았어요.",
      "exampleTranslation": "I found the lost key.",
      "timestamp": 110.6
    },
    {
      "korean": "함께",
      "romanization": "hamkke",
      "english": "together",
      "spanish": "juntos",
      "portuguese": "juntos",
      "indonesian": "bersama",
      "japanese": "一緒に",
      "thai": "ด้วยกัน",
      "french": "ensemble",
      "partOfSpeech": "adverb",
      "emoji": "🤝",
      "example": "친구와 함께 공부해요.",
      "exampleTranslation": "I study together with my friend.",
      "timestamp": 123.6
    },
    {
      "korean": "느낌",
      "romanization": "neukkim",
      "english": "feeling",
      "spanish": "sensación",
      "portuguese": "sensação",
      "indonesian": "perasaan",
      "japanese": "感じ",
      "thai": "ความรู้สึก",
      "french": "sensation",
      "partOfSpeech": "noun",
      "emoji": "💭",
      "example": "좋은 느낌이 들어요.",
      "exampleTranslation": "I have a good feeling.",
      "timestamp": 136.3
    },
    {
      "korean": "시작",
      "romanization": "sijak",
      "english": "beginning, start",
      "spanish": "comienzo",
      "portuguese": "início",
      "indonesian": "awal",
      "japanese": "始まり",
      "thai": "จุดเริ่มต้น",
      "french": "début",
      "partOfSpeech": "noun",
      "emoji": "🚀",
      "example": "새로운 시작을 응원해요.",
      "exampleTranslation": "I cheer for the new beginning.",
      "timestamp": 150.0
    },
    {
      "korean": "하늘",
      "romanization": "haneul",
      "english": "sky",
      "spanish": "cielo",
      "portuguese": "céu",
      "indonesian": "langit",
      "japanese": "空",
      "thai": "ท้องฟ้า",
      "french": "ciel",
      "partOfSpeech": "noun",
      "emoji": "☁️",
      "example": "오늘 하늘이 참 맑아요.",
      "exampleTranslation": "The sky is so clear today.",
      "timestamp": 162.8
    },
    {
      "korean": "하루",
      "romanization": "haru",
      "english": "a day",
      "spanish": "un día",
      "portuguese": "um dia",
      "indonesian": "satu hari",
      "japanese": "一日",
      "thai": "หนึ่งวัน",
      "french": "une journée",
      "partOfSpeech": "noun",
      "emoji": "📅",
      "example": "오늘 하루도 수고했어요.",
      "exampleTranslation": "Good work today too.",
      "timestamp": 169.6
    },
    {
      "korean": "안다",
      "romanization": "anda",
      "english": "to hug, to hold",
      "spanish": "abrazar",
      "portuguese": "abraçar",
      "indonesian": "memeluk",
      "japanese": "抱く",
      "thai": "กอด",
      "french": "embrasser",
      "partOfSpeech": "verb",
      "emoji": "🤗",
      "example": "아기를 꼭 안았어요.",
      "exampleTranslation": "I hugged the baby tightly.",
      "timestamp": 179.6
    },
    {
      "korean": "늦다",
      "romanization": "neutda",
      "english": "to be late",
      "spanish": "llegar tarde",
      "portuguese": "atrasar",
      "indonesian": "terlambat",
      "japanese": "遅れる",
      "thai": "สาย",
      "french": "être en retard",
      "partOfSpeech": "adjective",
      "emoji": "🕐",
      "example": "학교에 늦었어요.",
      "exampleTranslation": "I was late for school.",
      "timestamp": 192.5
    },
    {
      "korean": "날다",
      "romanization": "nalda",
      "english": "to fly",
      "spanish": "volar",
      "portuguese": "voar",
      "indonesian": "terbang",
      "japanese": "飛ぶ",
      "thai": "บิน",
      "french": "voler",
      "partOfSpeech": "verb",
      "emoji": "🕊️",
      "example": "새가 하늘을 날아요.",
      "exampleTranslation": "A bird flies in the sky.",
      "timestamp": 201.2
    },
    {
      "korean": "꿈",
      "romanization": "kkum",
      "english": "dream",
      "spanish": "sueño",
      "portuguese": "sonho",
      "indonesian": "mimpi",
      "japanese": "夢",
      "thai": "ความฝัน",
      "french": "rêve",
      "partOfSpeech": "noun",
      "emoji": "💫",
      "example": "저는 큰 꿈이 있어요.",
      "exampleTranslation": "I have a big dream.",
      "timestamp": 210.7
    },
    {
      "korean": "잠들다",
      "romanization": "jamdeulda",
      "english": "to fall asleep",
      "spanish": "dormirse",
      "portuguese": "adormecer",
      "indonesian": "tertidur",
      "japanese": "眠る",
      "thai": "หลับ",
      "french": "s'endormir",
      "partOfSpeech": "verb",
      "emoji": "😴",
      "example": "아이가 금방 잠들었어요.",
      "exampleTranslation": "The child fell asleep quickly.",
      "timestamp": 217.3
    },
    {
      "korean": "노래",
      "romanization": "norae",
      "english": "song",
      "spanish": "canción",
      "portuguese": "canção",
      "indonesian": "lagu",
      "japanese": "歌",
      "thai": "เพลง",
      "french": "chanson",
      "partOfSpeech": "noun",
      "emoji": "🎵",
      "example": "이 노래를 좋아해요.",
      "exampleTranslation": "I like this song.",
      "timestamp": 230.5
    },
    {
      "korean": "순간",
      "romanization": "sungan",
      "english": "moment",
      "spanish": "momento",
      "portuguese": "momento",
      "indonesian": "saat",
      "japanese": "瞬間",
      "thai": "ช่วงเวลา",
      "french": "instant",
      "partOfSpeech": "noun",
      "emoji": "⏱️",
      "example": "그 순간을 잊을 수 없어요.",
      "exampleTranslation": "I can't forget that moment.",
      "timestamp": 249.9
    },
    {
      "korean": "그립다",
      "romanization": "geuripda",
      "english": "to miss, to long for",
      "spanish": "echar de menos",
      "portuguese": "sentir saudade",
      "indonesian": "merindukan",
      "japanese": "恋しい",
      "thai": "คิดถึง",
      "french": "manquer",
      "partOfSpeech": "adjective",
      "emoji": "🥺",
      "example": "고향이 그리워요.",
      "exampleTranslation": "I miss my hometown.",
      "timestamp": 256.4
    }
  ]
}
