{
  "id": "ive-rebel-heart",
  "title": "REBEL HEART",
  "artist": "IVE",
  "youtubeId": "g36q0ZLvygQ",
  "words": [
    {
      "korean": "시작",
      "romanization": "sijak",
      "english": "start, beginning",
      "spanish": "comienzo",
      "portuguese": "início",
      "indonesian": "awal",
      "japanese": "始まり",
      "thai": "การเริ่มต้น",
      "french": "début",
      "partOfSpeech": "noun",
      "emoji": "🏁",
      "example": "새로운 시작을 응원해요.",
      "exampleTranslation": "I'm cheering for a new start.",
      "timestamp": 3.8
    },
    {
      "korean": "항상",
      "romanization": "hangsang",
      "english": "always",
      "spanish": "siempre",
      "portuguese": "sempre",
      "indonesian": "selalu",
      "japanese": "いつも",
      "thai": "เสมอ",
      "french": "toujours",
      "partOfSpeech": "adverb",
      "emoji": "♾️",
      "example": "항상 널 응원할게요.",
      "exampleTranslation": "I'll always support you.",
      "timestamp": 3.8
    },
    {
      "korean": "이룬",
      "romanization": "irun",
      "english": "achieved, accomplished",
      "spanish": "logrado",
      "portuguese": "realizado",
      "indonesian": "yang tercapai",
      "japanese": "成し遂げた",
      "thai": "ที่สำเร็จ",
      "french": "accompli",
      "partOfSpeech": "verb",
      "emoji": "🏆",
      "example": "꿈을 다 이룬 기분이에요.",
      "exampleTranslation": "I feel like I've achieved everything.",
      "timestamp": 3.8
    },
    {
      "korean": "마치",
      "romanization": "machi",
      "english": "as if, just like",
      "spanish": "como si",
      "portuguese": "como se",
      "indonesian": "seolah-olah",
      "japanese": "まるで",
      "thai": "ราวกับ",
      "french": "comme si",
      "partOfSpeech": "adverb",
      "emoji": "🎭",
      "example": "마치 영화 같은 순간이었어요.",
      "exampleTranslation": "It was a moment just like a movie.",
      "timestamp": 7.4
    },
    {
      "korean": "승리한",
      "romanization": "seungrihan",
      "english": "victorious",
      "spanish": "victorioso",
      "portuguese": "vitorioso",
      "indonesian": "yang menang",
      "japanese": "勝利した",
      "thai": "ที่ชนะ",
      "french": "victorieux",
      "partOfSpeech": "verb",
      "emoji": "🥇",
      "example": "승리한 팀이 환호했어요.",
      "exampleTranslation": "The victorious team cheered.",
      "timestamp": 7.4
    },
    {
      "korean": "겁내지",
      "romanization": "geomnaeji",
      "english": "don't be afraid",
      "spanish": "no temas",
      "portuguese": "não tenha medo",
      "indonesian": "jangan takut",
      "japanese": "怖がらないで",
      "thai": "อย่ากลัว",
      "french": "n'aie pas peur",
      "partOfSpeech": "verb",
      "emoji": "💪",
      "example": "겁내지 말고 도전해요.",
      "exampleTranslation": "Don't be afraid, take on the challenge.",
      "timestamp": 11.4
    },
    {
      "korean": "마음",
      "romanization": "maeum",
      "english": "heart, mind",
      "spanish": "corazón",
      "portuguese": "coração",
      "indonesian": "hati",
      "japanese": "心",
      "thai": "ใจ",
      "french": "cœur",
      "partOfSpeech": "noun",
      "emoji": "💗",
      "example": "온 마음을 다해 노래해요.",
      "exampleTranslation": "I sing with all my heart.",
      "timestamp": 11.4
    },
    {
      "korean": "모양",
      "romanization": "moyang",
      "english": "shape, form",
      "spanish": "forma",
      "portuguese": "forma",
      "indonesian": "bentuk",
      "japanese": "形",
      "thai": "รูปทรง",
      "french": "forme",
      "partOfSpeech": "noun",
      "emoji": "🔷",
      "example": "내 모양대로 살고 싶어요.",
      "exampleTranslation": "I want to live in my own way.",
      "timestamp": 15.3
    },
    {
      "korean": "이제",
      "romanization": "ije",
      "english": "now, from now on",
      "spanish": "ahora",
      "portuguese": "agora",
      "indonesian": "sekarang",
      "japanese": "もう",
      "thai": "ตอนนี้",
      "french": "maintenant",
      "partOfSpeech": "adverb",
      "emoji": "🕐",
      "example": "이제 더 이상 참지 않아요.",
      "exampleTranslation": "I won't put up with it anymore.",
      "timestamp": 18.8
    },
    {
      "korean": "신경",
      "romanization": "singyeong",
      "english": "care, attention, nerves",
      "spanish": "preocupación",
      "portuguese": "preocupação",
      "indonesian": "peduli",
      "japanese": "気にすること",
      "thai": "การใส่ใจ",
      "french": "souci",
      "partOfSpeech": "noun",
      "emoji": "🧠",
      "example": "남의 말에 신경 쓰지 않아요.",
      "exampleTranslation": "I don't care about what others say.",
      "timestamp": 18.8
    },
    {
      "korean": "지키기",
      "romanization": "jikigi",
      "english": "protecting, keeping",
      "spanish": "proteger",
      "portuguese": "proteger",
      "indonesian": "menjaga",
      "japanese": "守ること",
      "thai": "การปกป้อง",
      "french": "protéger",
      "partOfSpeech": "verb",
      "emoji": "🛡️",
      "example": "내 마음을 지키기로 했어요.",
      "exampleTranslation": "I decided to protect my heart.",
      "timestamp": 22.5
    },
    {
      "korean": "오해",
      "romanization": "ohae",
      "english": "misunderstanding",
      "spanish": "malentendido",
      "portuguese": "mal-entendido",
      "indonesian": "salah paham",
      "japanese": "誤解",
      "thai": "ความเข้าใจผิด",
      "french": "malentendu",
      "partOfSpeech": "noun",
      "emoji": "🤨",
      "example": "작은 오해가 생겼어요.",
      "exampleTranslation": "A small misunderstanding arose.",
      "timestamp": 26.3
    },
    {
      "korean": "자유",
      "romanization": "jayu",
      "english": "freedom",
      "spanish": "libertad",
      "portuguese": "liberdade",
      "indonesian": "kebebasan",
      "japanese": "自由",
      "thai": "อิสรภาพ",
      "french": "liberté",
      "partOfSpeech": "noun",
      "emoji": "🕊️",
      "example": "자유를 향해 나아가요.",
      "exampleTranslation": "I move forward toward freedom.",
      "timestamp": 26.3
    },
    {
      "korean": "꺾이지",
      "romanization": "kkeokiji",
      "english": "won't be broken, unbowed",
      "spanish": "no se doblega",
      "portuguese": "não se quebra",
      "indonesian": "tidak patah",
      "japanese": "折れない",
      "thai": "ไม่ยอมแพ้",
      "french": "ne pas fléchir",
      "partOfSpeech": "verb",
      "emoji": "🔥",
      "example": "우리는 절대 꺾이지 않아요.",
      "exampleTranslation": "We will never be broken.",
      "timestamp": 56.2
    },
    {
      "korean": "부족해",
      "romanization": "bujokae",
      "english": "lacking, not enough",
      "spanish": "insuficiente",
      "portuguese": "insuficiente",
      "indonesian": "kurang",
      "japanese": "足りない",
      "thai": "ขาด",
      "french": "insuffisant",
      "partOfSpeech": "adjective",
      "emoji": "📉",
      "example": "너는 어디가 조금 부족해요.",
      "exampleTranslation": "You're a little lacking somewhere.",
      "timestamp": 65.2
    },
    {
      "korean": "넘쳐",
      "romanization": "neomchyeo",
      "english": "to overflow",
      "spanish": "desbordar",
      "portuguese": "transbordar",
      "indonesian": "meluap",
      "japanese": "あふれる",
      "thai": "ล้น",
      "french": "déborder",
      "partOfSpeech": "verb",
      "emoji": "🌊",
      "example": "자신감이 넘쳐요.",
      "exampleTranslation": "I'm overflowing with confidence.",
      "timestamp": 65.2
    },
    {
      "korean": "실행",
      "romanization": "silhaeng",
      "english": "execution, putting into action",
      "spanish": "ejecución",
      "portuguese": "execução",
      "indonesian": "pelaksanaan",
      "japanese": "実行",
      "thai": "การลงมือทำ",
      "french": "exécution",
      "partOfSpeech": "noun",
      "emoji": "🎯",
      "example": "말보다 실행이 중요해요.",
      "exampleTranslation": "Action matters more than words.",
      "timestamp": 69.2
    },
    {
      "korean": "외로움",
      "romanization": "oeroum",
      "english": "loneliness",
      "spanish": "soledad",
      "portuguese": "solidão",
      "indonesian": "kesepian",
      "japanese": "孤独",
      "thai": "ความเหงา",
      "french": "solitude",
      "partOfSpeech": "noun",
      "emoji": "🌙",
      "example": "밤이면 외로움이 밀려와요.",
      "exampleTranslation": "Loneliness washes over me at night.",
      "timestamp": 80.3
    },
    {
      "korean": "이유",
      "romanization": "iyu",
      "english": "reason",
      "spanish": "razón",
      "portuguese": "razão",
      "indonesian": "alasan",
      "japanese": "理由",
      "thai": "เหตุผล",
      "french": "raison",
      "partOfSpeech": "noun",
      "emoji": "❔",
      "example": "따로 이유를 묻지 않아요.",
      "exampleTranslation": "I don't ask for a reason.",
      "timestamp": 136.7
    },
    {
      "korean": "영원",
      "romanization": "yeongwon",
      "english": "eternity, forever",
      "spanish": "eternidad",
      "portuguese": "eternidade",
      "indonesian": "keabadian",
      "japanese": "永遠",
      "thai": "ชั่วนิรันดร์",
      "french": "éternité",
      "partOfSpeech": "noun",
      "emoji": "💍",
      "example": "영원을 약속했어요.",
      "exampleTranslation": "We promised forever.",
      "timestamp": 144.4
    }
  ]
}