{
  "id": "nmixx-dash-sync",
  "title": "DASH",
  "artist": "NMIXX",
  "youtubeId": "7UecFm_bSTU",
  "words": [
    {
      "korean": "없이",
      "romanization": "eopsi",
      "english": "without",
      "spanish": "",
      "portuguese": "",
      "indonesian": "",
      "japanese": "",
      "thai": "",
      "french": "",
      "partOfSpeech": "adverb",
      "emoji": "🚫",
      "example": "걱정 없이 살고 싶어요.",
      "exampleTranslation": "I want to live without worries.",
      "timestamp": 12
    },
    {
      "korean": "막아선",
      "romanization": "magaseon",
      "english": "blocked / stood in the way",
      "spanish": "",
      "portuguese": "",
      "indonesian": "",
      "japanese": "",
      "thai": "",
      "french": "",
      "partOfSpeech": "verb",
      "emoji": "🛑",
      "example": "길을 막아선 사람이 있었어요.",
      "exampleTranslation": "There was someone blocking the way.",
      "timestamp": 15
    },
    {
      "korean": "사뿐히",
      "romanization": "sappunhi",
      "english": "lightly / softly",
      "spanish": "",
      "portuguese": "",
      "indonesian": "",
      "japanese": "",
      "thai": "",
      "french": "",
      "partOfSpeech": "adverb",
      "emoji": "🦋",
      "example": "사뿐히 걸었어요.",
      "exampleTranslation": "I walked lightly.",
      "timestamp": 17
    },
    {
      "korean": "깜빡여",
      "romanization": "kkamppagyeo",
      "english": "blink / flicker",
      "spanish": "",
      "portuguese": "",
      "indonesian": "",
      "japanese": "",
      "thai": "",
      "french": "",
      "partOfSpeech": "verb",
      "emoji": "✨",
      "example": "별이 깜빡여요.",
      "exampleTranslation": "The stars are flickering.",
      "timestamp": 21
    },
    {
      "korean": "이건",
      "romanization": "igeon",
      "english": "this is",
      "spanish": "",
      "portuguese": "",
      "indonesian": "",
      "japanese": "",
      "thai": "",
      "french": "",
      "partOfSpeech": "noun",
      "emoji": "👉",
      "example": "이건 뭐예요?",
      "exampleTranslation": "What is this?",
      "timestamp": 23
    },
    {
      "korean": "고민",
      "romanization": "gomin",
      "english": "worry / concern",
      "spanish": "",
      "portuguese": "",
      "indonesian": "",
      "japanese": "",
      "thai": "",
      "french": "",
      "partOfSpeech": "noun",
      "emoji": "😟",
      "example": "고민이 많아요.",
      "exampleTranslation": "I have many worries.",
      "timestamp": 29
    },
    {
      "korean": "떨리는",
      "romanization": "tteollineun",
      "english": "trembling",
      "spanish": "",
      "portuguese": "",
      "indonesian": "",
      "japanese": "",
      "thai": "",
      "french": "",
      "partOfSpeech": "adjective",
      "emoji": "😰",
      "example": "떨리는 손으로 편지를 썼어요.",
      "exampleTranslation": "I wrote a letter with trembling hands.",
      "timestamp": 31
    },
    {
      "korean": "멀리",
      "romanization": "meolli",
      "english": "far away",
      "spanish": "",
      "portuguese": "",
      "indonesian": "",
      "japanese": "",
      "thai": "",
      "french": "",
      "partOfSpeech": "adverb",
      "emoji": "🏔️",
      "example": "멀리 보이는 산이 예뻐요.",
      "exampleTranslation": "The mountain visible far away is pretty.",
      "timestamp": 34
    },
    {
      "korean": "끌어올려",
      "romanization": "kkeuroollyeo",
      "english": "pull up / raise",
      "spanish": "",
      "portuguese": "",
      "indonesian": "",
      "japanese": "",
      "thai": "",
      "french": "",
      "partOfSpeech": "verb",
      "emoji": "⬆️",
      "example": "기분을 끌어올려요.",
      "exampleTranslation": "I lift up my mood.",
      "timestamp": 42
    },
    {
      "korean": "세상이",
      "romanization": "sesangi",
      "english": "the world (subject)",
      "spanish": "",
      "portuguese": "",
      "indonesian": "",
      "japanese": "",
      "thai": "",
      "french": "",
      "partOfSpeech": "noun",
      "emoji": "🌍",
      "example": "세상이 아름다워요.",
      "exampleTranslation": "The world is beautiful.",
      "timestamp": 47
    },
    {
      "korean": "심장은",
      "romanization": "simjangeun",
      "english": "the heart (topic)",
      "spanish": "",
      "portuguese": "",
      "indonesian": "",
      "japanese": "",
      "thai": "",
      "french": "",
      "partOfSpeech": "noun",
      "emoji": "❤️",
      "example": "심장은 빠르게 뛰어요.",
      "exampleTranslation": "My heart beats fast.",
      "timestamp": 70
    },
    {
      "korean": "꿈꿔왔던",
      "romanization": "kkumkkwowatdeon",
      "english": "had been dreaming of",
      "spanish": "",
      "portuguese": "",
      "indonesian": "",
      "japanese": "",
      "thai": "",
      "french": "",
      "partOfSpeech": "verb",
      "emoji": "💭",
      "example": "꿈꿔왔던 무대에 섰어요.",
      "exampleTranslation": "I stood on the stage I had been dreaming of.",
      "timestamp": 72
    },
    {
      "korean": "언제나",
      "romanization": "eonjena",
      "english": "always",
      "spanish": "",
      "portuguese": "",
      "indonesian": "",
      "japanese": "",
      "thai": "",
      "french": "",
      "partOfSpeech": "adverb",
      "emoji": "♾️",
      "example": "언제나 응원할게요.",
      "exampleTranslation": "I will always support you.",
      "timestamp": 80
    },
    {
      "korean": "누구든",
      "romanization": "nugudeun",
      "english": "whoever / anyone",
      "spanish": "",
      "portuguese": "",
      "indonesian": "",
      "japanese": "",
      "thai": "",
      "french": "",
      "partOfSpeech": "noun",
      "emoji": "👥",
      "example": "누구든 환영해요.",
      "exampleTranslation": "Anyone is welcome.",
      "timestamp": 83
    },
    {
      "korean": "지나간",
      "romanization": "jinagan",
      "english": "passed / gone by",
      "spanish": "",
      "portuguese": "",
      "indonesian": "",
      "japanese": "",
      "thai": "",
      "french": "",
      "partOfSpeech": "adjective",
      "emoji": "⏪",
      "example": "지나간 시간은 돌아오지 않아요.",
      "exampleTranslation": "Time that has passed doesn't come back.",
      "timestamp": 85
    },
    {
      "korean": "앞을",
      "romanization": "apeul",
      "english": "the front (object)",
      "spanish": "",
      "portuguese": "",
      "indonesian": "",
      "japanese": "",
      "thai": "",
      "french": "",
      "partOfSpeech": "noun",
      "emoji": "👉",
      "example": "앞을 봐요.",
      "exampleTranslation": "Look ahead.",
      "timestamp": 87
    },
    {
      "korean": "시작해",
      "romanization": "sijakae",
      "english": "start / begin",
      "spanish": "",
      "portuguese": "",
      "indonesian": "",
      "japanese": "",
      "thai": "",
      "french": "",
      "partOfSpeech": "verb",
      "emoji": "▶️",
      "example": "지금 시작해요!",
      "exampleTranslation": "Let's start now!",
      "timestamp": 96
    },
    {
      "korean": "또다시",
      "romanization": "ttodasi",
      "english": "once again",
      "spanish": "",
      "portuguese": "",
      "indonesian": "",
      "japanese": "",
      "thai": "",
      "french": "",
      "partOfSpeech": "adverb",
      "emoji": "🔄",
      "example": "또다시 도전해요.",
      "exampleTranslation": "I challenge again.",
      "timestamp": 115
    },
    {
      "korean": "거친",
      "romanization": "geochin",
      "english": "rough / wild",
      "spanish": "",
      "portuguese": "",
      "indonesian": "",
      "japanese": "",
      "thai": "",
      "french": "",
      "partOfSpeech": "adjective",
      "emoji": "🌊",
      "example": "거친 바람이 불어요.",
      "exampleTranslation": "A rough wind is blowing.",
      "timestamp": 118
    },
    {
      "korean": "겁낼",
      "romanization": "geomnael",
      "english": "to be afraid",
      "spanish": "",
      "portuguese": "",
      "indonesian": "",
      "japanese": "",
      "thai": "",
      "french": "",
      "partOfSpeech": "verb",
      "emoji": "😨",
      "example": "겁낼 필요 없어요.",
      "exampleTranslation": "There's no need to be afraid.",
      "timestamp": 123
    }
  ]
}
